aiandme_cli/__init__.py
aiandme_cli/client.py
aiandme_cli/config.py
aiandme_cli/exceptions.py
aiandme_cli/main.py
aiandme_cli/commands/__init__.py
aiandme_cli/commands/auth.py
aiandme_cli/commands/docs.py
aiandme_cli/commands/experiments.py
aiandme_cli/commands/guardrails.py
aiandme_cli/commands/init.py
aiandme_cli/commands/logs.py
aiandme_cli/commands/orgs.py
aiandme_cli/commands/posture.py
aiandme_cli/commands/projects.py
aiandme_cli/commands/providers.py
aiandme_cli/commands/scan.py
aiandme_cli/commands/test.py
aiandme_cli/extractors/__init__.py
aiandme_cli/extractors/openapi.py
aiandme_cli/extractors/repo.py
aiandme_cli/pytest_plugin/__init__.py
aiandme_cli/pytest_plugin/fixtures.py
aiandme_cli/pytest_plugin/report.py
tests/__init__.py
tests/cli_integration_test.py
tests/conftest.py
tests/test_cli_commands.py
aiandme_cli-0.1.3.dist-info/LICENSE
aiandme_cli-0.1.3.dist-info/METADATA
aiandme_cli-0.1.3.dist-info/WHEEL
aiandme_cli-0.1.3.dist-info/entry_points.txt
aiandme_cli-0.1.3.dist-info/top_level.txt
aiandme_cli-0.1.3.dist-info/RECORD
