Metadata-Version: 2.1
Name: aiandme-cli
Version: 0.1.3
Summary: AIandMe CLI - command line interface for AI agent security testing.
Author-email: Kostas Siabanis <hello@aiandme.io>, Demetris Gerogiannis <hello@aiandme.io>
License: Apache-2.0
Project-URL: Homepage, https://github.com/aiandme-io/aiandme-cli
Project-URL: Documentation, https://docs.aiandme.io/cli
Project-URL: Issues, https://github.com/aiandme-io/aiandme-cli/issues
Classifier: Programming Language :: Python :: 3
Classifier: License :: OSI Approved :: Apache Software License
Classifier: Operating System :: OS Independent
Classifier: Environment :: Console
Classifier: Framework :: Pytest
Requires-Python: >=3.10
License-File: LICENSE
Requires-Dist: click >=8.1.0
Requires-Dist: rich >=13.0.0
Requires-Dist: requests >=2.32.0
Requires-Dist: pyyaml >=6.0.0
Provides-Extra: dev
Requires-Dist: pytest >=7.0.0 ; extra == 'dev'
Requires-Dist: pytest-cov >=4.0.0 ; extra == 'dev'
Provides-Extra: pytest
Requires-Dist: pytest >=7.0.0 ; extra == 'pytest'
